{
  "$schema": "https://json-schema.org/draft/2020-12/schema",
  "$id": "https://ucp.dev/2026-01-23/schemas/shopping/checkout.json",
  "name": "dev.ucp.shopping.checkout",
  "version": "2026-01-11",
  "title": "Checkout Response",
  "description": "Base checkout schema. Extensions compose onto this using allOf.",
  "type": "object",
  "required": ["id"],
  "additionalProperties": true,
  "properties": {
    "id": {
      "type": "string",
      "description": "Unique identifier of the checkout session."
    }
  }
}
